tf_env/__init__.py
tf_env/anyrl_env.py
tf_env/base.py
tf_env/point_seeker.py
tf_env/pong.py
tf_env/util.py
tf_env-0.1.0.dist-info/METADATA
tf_env-0.1.0.dist-info/RECORD
tf_env-0.1.0.dist-info/WHEEL
tf_env-0.1.0.dist-info/top_level.txt
