Metadata-Version: 2.1
Name: tf-env
Version: 0.1.0
Summary: RL environments for TensorFlow.
Home-page: https://github.com/unixpickle/tf-env
Author: Alex Nichol
Author-email: unixpickle@gmail.com
License: UNKNOWN
Platform: UNKNOWN
Provides-Extra: tf_gpu
Provides-Extra: tf
Requires-Dist: numpy
Requires-Dist: anyrl (<0.13.0,>=0.11.0)
Provides-Extra: tf
Requires-Dist: tensorflow (>=1.4.0); extra == 'tf'
Provides-Extra: tf_gpu
Requires-Dist: tensorflow-gpu (>=1.4.0); extra == 'tf_gpu'
